filevault
