Metadata-Version: 1.0
Name: filevault
Version: 0.1.2
Summary: filevault: manage a hash directory tree and files
Home-page: https://bitbucket.org/russellballestrini/filevault/src
Author: Russell Ballestrini
Author-email: russell@ballestrini.net
License: Public Domain
Keywords: file vault filevault hashed hash directory tree directories dir obfuscate hex
Platform: All
